{
  "listen": {
    "host": "127.0.0.1",
    "port": 3101
  },
  "flags": {

  },
  "passport": {
    "local": {
      "usernameField": "email",
      "passwordField": "password",
      "session": true,
      "passReqToCallback": false
    },
    "oauth2": {
      "authorizationURL": "https://live.durhack.com/login/authorize",
      "tokenURL": "https://live.durhack.com/api/auth/token",
      "clientID": "megateams",
      "clientSecret": "this-is-not-a-real-client-secret",
      "callbackURL": "https://megateams.durhack.com/api/auth/durhack-live/callback",
      "state": true,
      "scope": ["api"],
      "pkce": true,
      "profileURL": "https://live.durhack.com/api/user"
    }
  },
  "mysql": {
    "data": {
      "host": "127.0.0.1",
      "port": 3306,
      "database": "durhack",
      "user": "root",
      "password": "strongexamplepassword"
    },
    "session": {
      "host": "127.0.0.1",
      "port": 3306,
      "database": "durhack-session",
      "user": "root",
      "password": "strongexamplepassword"
    }
  },
  "csrf": {
    "enabled": true,
    "secret": "csrfisoverrated",
    "options": {
      "cookieName": "psifi.x-csrf-token",
      "cookieOptions": {
        "sameSite": "strict",
        "path": "/",
        "secure": false
      }
    }
  },
  "cookie-parser": {
    "secret": "thebestsecretforcookies"
  },
  "session": {
    "name": "durhack-megateams-session",
    "secret": "session_cookie_secret",
    "resave": false,
    "saveUninitialized": false,
    "cookie": { "secure": false }
  },
  "megateams": {
    "maxTeamMembers": 4,
    "QRCodeRedemptionURL": "https://megateams.durhack.com/hacker/redeem",
    "QRPresets": {
      "5points": {
        "name": "5 Points",
        "description": "A single-use QR to reward hacker engagement.",
        "points": 5,
        "uses": 1,
        "minutesValid": 2
      },
      "10points": {
        "name": "10 Points",
        "description": "A single-use QR to give a larger reward to a hacker.",
        "points": 10,
        "uses": 1,
        "minutesValid": 2
      }
    }
  },
  "discord": {
    "apiEndpoint": "https://discord.com/api/v10",
    "clientId": "yourDiscordAppClientIdHere",
    "clientSecret": "yourDiscordAppClientSecretHere",
    "redirectUri": "http://localhost:3101/api/discord/redirect",
    "botToken": "yourDiscordBotTokenHere",
    "guildID": "yourDiscordGuildIDHere",
    "inviteLink": "https://discord.gg/xyz",
    "teamsParentChannel": "yourTeamsParentChannelIdHere"
  }
}